{
  "rules": {
    "users": {
      "$userId": {
        ".read": "auth != null",
        ".write": "auth != null && auth.uid == $userId",
        ".validate": "newData.hasChildren(['email', 'name', 'uid']) && 
                     newData.child('email').isString() && 
                     newData.child('name').isString() && 
                     newData.child('uid').isString()"
      }
    },
    "notifications": {
      "$userId": {
        ".read": "auth != null && auth.uid == $userId",
        ".write": "auth != null && (auth.uid == $userId || auth.token.admin == true)",
        "$notificationId": {
          ".validate": "newData.hasChildren(['type', 'title', 'message', 'timestamp', 'read']) && 
                       newData.child('type').isString() && 
                       newData.child('title').isString() && 
                       newData.child('message').isString() && 
                       newData.child('timestamp').isString() && 
                       newData.child('read').isBoolean()"
        }
      }
    }
  }
}